tornadoist2
