Metadata-Version: 1.1
Name: tornadoist2
Version: 0.2.1
Summary: mixins for tornado
Home-page: https://github.com/badbye/tornadoist.git
Author: Eren Güven, Yalei Du
Author-email: erenguven0@gmail.com
License: Apache License, Version 2
Keywords: tornado,celery
Platform: UNKNOWN
Classifier: Development Status :: 3 - Alpha
Classifier: Programming Language :: Python :: 2.6
Classifier: Programming Language :: Python :: 2.7
Classifier: Topic :: Utilities
Classifier: License :: OSI Approved :: Apache Software License
